svalinn_tools/__init__.py
svalinn_tools/data_loading.py
svalinn_tools/graveyard_removal.py
svalinn_tools/tag_expansion.py
svalinn_tools/img/README_example.png
svalinn_tools/img/svalinn.png
svalinn_tools-0.3.dist-info/LICENSE.md
svalinn_tools-0.3.dist-info/METADATA
svalinn_tools-0.3.dist-info/WHEEL
svalinn_tools-0.3.dist-info/entry_points.txt
svalinn_tools-0.3.dist-info/top_level.txt
svalinn_tools-0.3.dist-info/RECORD
