Metadata-Version: 2.1
Name: svalinn-tools
Version: 0.3
Summary: DAGMC Visualization Tools
Home-page: https://github.com/svalinn/DAGMC-viz
Author: Svalinn Development Team
License: UNKNOWN
Platform: UNKNOWN
Classifier: Programming Language :: Python :: 2.7
Requires-Dist: numpy
